testmarker/__init__.py
testmarker/__main__.py
testmarker/setupcmd.py
testmarker-0.1.3.dist-info/DESCRIPTION.rst
testmarker-0.1.3.dist-info/METADATA
testmarker-0.1.3.dist-info/RECORD
testmarker-0.1.3.dist-info/WHEEL
testmarker-0.1.3.dist-info/entry_points.txt
testmarker-0.1.3.dist-info/metadata.json
testmarker-0.1.3.dist-info/top_level.txt
