Metadata-Version: 2.0
Name: testmarker
Version: 0.1.3
Summary: marker for unittest (stdlib)
Home-page: https://github.com/podhmo/testmarker
Author: podhmo
Author-email: ababjam61+github@gmail.com
License: UNKNOWN
Keywords: unittest marker
Platform: UNKNOWN
Classifier: Programming Language :: Python
Classifier: Programming Language :: Python :: Implementation :: CPython
Provides-Extra: docs
Requires-Dist: kamidana; extra == 'docs'
Provides-Extra: testing
